m5pre.py
m5pre-1.0.3.dist-info/LICENSE
m5pre-1.0.3.dist-info/METADATA
m5pre-1.0.3.dist-info/WHEEL
m5pre-1.0.3.dist-info/top_level.txt
m5pre-1.0.3.dist-info/RECORD
